sprained
