Metadata-Version: 1.1
Name: sprained
Version: 0.007
Summary: An integration of the spread toolkit, (http://spread.org), with twisted.
Home-page: http://packages.python.org/sprained
Author: K. Richard Pixley
Author-email: rich@noir.com
License: MIT
Keywords: twisted spread
Platform: UNKNOWN
Classifier: Development Status :: 2 - Pre-Alpha
Classifier: Framework :: Twisted
Classifier: Intended Audience :: Developers
Classifier: License :: OSI Approved :: MIT License
Classifier: Natural Language :: English
Classifier: Operating System :: OS Independent
Classifier: Programming Language :: Python
Classifier: Programming Language :: Python :: 2.6
Classifier: Topic :: Software Development :: Libraries :: Python Modules
Classifier: Topic :: System :: Networking
Requires: collections
Requires: metaserializer
Requires: os
Requires: spread
Requires: twisted.internet
Requires: zope.interface
Provides: sprained
